{
  "claim_id": "C047",
  "schema_version": "1.0",
  "run_id": "run_20260419T0032Z",
  "citekey": "uecker2014",
  "handle": "pdfs/uecker2014/",
  "ingest_mode": "error",
  "source_ref_urls": [],
  "claim_text": "network.2 The UNet models followed the architecture in the fastMRI challenge,42 while the unrolled models followed the fast iterative shrinkage-thresholding algorithm (FISTA) unrolled architecture43 implemented in.2 Reference images were computed from the fully sampled k-space data with the eSPIRIT method to integrate coil sensitivities.44 The magnitude of the complex image data was taken for both the evaluation by radiologists and the computation of IQ metrics.",
  "manuscript_section": "**Citekey:** `uecker2014` (ref #44)",
  "claim_type": {
    "type": "DIRECT",
    "confidence": "medium"
  },
  "sub_claims": [
    {
      "sub_claim_id": "C047.a",
      "text": "network.2 The UNet models followed the architecture in the fastMRI challenge,42 while the unrolled models followed the fast iterative shrinkage-thresholding algorithm (FISTA) unrolled architecture43 i",
      "evidence": [],
      "figures_checked": [],
      "verdict": "PENDING",
      "paper_value": null,
      "claim_value": null,
      "nuance": "Source PDF unavailable (paywalled or fetch failed); cannot ground."
    }
  ],
  "overall_verdict": "PENDING",
  "overall_flag": "NEEDS_PDF",
  "remediation": null,
  "attestation": {
    "phrasings_tried": [],
    "section_checklist": [],
    "closest_adjacent": null,
    "indirect_attribution_check": null,
    "out_of_context_check": null
  },
  "co_cite_context": {
    "sibling_citekeys": [
      "sandino2020",
      "knoll2020"
    ],
    "sibling_verdicts": []
  },
  "stage": "stub"
}